statica/__init__.py
statica/config.py
statica/core.py
statica/exceptions.py
statica/validation.py
statica-1.4.0.dist-info/METADATA
statica-1.4.0.dist-info/WHEEL
statica-1.4.0.dist-info/top_level.txt
statica-1.4.0.dist-info/RECORD
