Metadata-Version: 2.4
Name: statica
Version: 1.4.0
Summary: A minimalistic data validation library
Author-email: Marcel Kröker <kroeker.marcel@gmail.com>
License: MIT License
Classifier: Programming Language :: Python :: 3
Classifier: License :: OSI Approved :: MIT License
Classifier: Operating System :: OS Independent
Classifier: Intended Audience :: Developers
Classifier: Programming Language :: Python
Classifier: Topic :: Software Development :: Libraries :: Python Modules
Requires-Python: <3.14,>=3.11
